tests
pyinter
