Metadata-Version: 1.1
Name: pyinter
Version: 0.1.4
Summary: An interval package for Python.
Home-page: intiocean.com
Author: Inti Ocean
Author-email: intiocean@gmail.com
License: MIT
Keywords: interval range discontinous-range union intersection
Platform: UNKNOWN
Classifier: Development Status :: 3 - Alpha
Classifier: License :: OSI Approved :: MIT License
